{
    "Dict": {
        "act3mainss_zone1": {
            "nameCN": "Episode 16 : 反常光谱",
            "nameEN": "Episode 16 : Abnormal Spectrum",
            "startCN": -1
        },
        "act2multi": {
            "nameCN": "促融共竞#2",
            "nameEN": "Icebreaker Games #2",
            "startCN": 1761033600
        },
        "act1vhalfidle": {
            "nameCN": "次生预案",
            "nameEN": "Rebuilding Mandate",
            "startCN": 1758787200
        },
        "act37sre": {
            "nameCN": "追迹日落以西·复刻",
            "nameEN": "Ending a Grand Overture - Rerun",
            "startCN": 1758268800
        },
        "act45side": {
            "nameCN": "无忧梦呓",
            "nameEN": "Somniloquium Serenum",
            "startCN": 1756958400
        },
        "act2enemyduel": {
            "nameCN": "争锋频道：蜜果城",
            "nameEN": "Duel Channel: Honeydew",
            "startCN": 1756368000
        },
        "act35sre": {
            "nameCN": "太阳甩在身后·复刻",
            "nameEN": "Adventure That Cannot Wait for the Sun - Rerun",
            "startCN": 1756065600
        },
        "act44side": {
            "nameCN": "墟",
            "nameEN": "Ato",
            "startCN": 1754107200
        },
        "act19mini": {
            "nameCN": "镜中集",
            "nameEN": "Fantasy in The Mirage",
            "startCN": 1751947200
        },
        "act5bossrush": {
            "nameCN": "引航者试炼",
            "nameEN": "Trials for Navigator #5",
            "startCN": 1750752000
        },
        "act43side": {
            "nameCN": "红丝绒",
            "nameEN": "Act or Die",
            "startCN": 1749096000
        },
        "act34sre": {
            "nameCN": "生路·复刻",
            "nameEN": "Path of Life - Rerun",
            "startCN": 1750320000
        },
        "act1break": {
            "nameCN": "矢量突破：无机物",
            "nameEN": "Vector Breakthrough #1 : Mechanist",
            "startCN": 1747296000
        },
        "act42side": {
            "nameCN": "众生行记",
            "nameEN": "The Masses' Travels",
            "startCN": 1746072000
        },
        "act1enemyduel": {
            "nameCN": "争锋频道：青草城",
            "nameEN": "Duel Channel: Green Grass",
            "startCN": 1745674200
        },
        "act33sre": {
            "nameCN": "巴别塔·复刻",
            "nameEN": "Babel - Rerun",
            "startCN": 1745222400
        },
        "act2mainss_zone1": {
            "nameCN": "Episode 15 : 离解复合",
            "nameEN": "Episode 15 : Dissociative Recombination",
            "startCN": -1
        },
        "act1multi": {
            "nameCN": "促融共竞#1",
            "nameEN": "Icebreaker Games #1",
            "startCN": 1742457600
        },
        "act41side": {
            "nameCN": "挽歌燃烧殆尽",
            "nameEN": "When Elegies Are Ashes",
            "startCN": 1741320000
        },
        "act40side": {
            "nameCN": "相见欢",
            "nameEN": "Such is the Joy of Our Reunion",
            "startCN": 1737518400
        },
        "act18mini": {
            "nameCN": "我们明日见",
            "nameEN": "See You Soon",
            "startCN": 1739520000
        },
        "act31sre": {
            "nameCN": "怀黍离·复刻",
            "nameEN": "Here A People Sows - Rerun",
            "startCN": 1740384000
        },
        "act1arcade": {
            "nameCN": "视相博物馆",
            "nameEN": "Poly Vision Museum",
            "startCN": 1735459200
        },
        "act30sre": {
            "nameCN": "银心湖列车·复刻",
            "nameEN": "The Rides to Lake Silberneherze - Rerun",
            "startCN": 1734595200
        },
        "act39side": {
            "nameCN": "出苍白海",
            "nameEN": "Exodus from the Pale Sea",
            "startCN": 1733371200
        },
        "act1vautochess": {
            "nameCN": "卫戍协议",
            "nameEN": "Stronghold Protocol",
            "startCN": 1731657600
        },
        "act29sre": {
            "nameCN": "崔林特尔梅之金·复刻",
            "nameEN": "Zwillingstürme im Herbst - Rerun",
            "startCN": 1732521600
        },
        "act38side": {
            "nameCN": "揭幕者们",
            "nameEN": "I Portatori dei Velluti",
            "startCN": 1730433600
        },
        "act37side": {
            "nameCN": "追迹日落以西",
            "nameEN": "Ending a Grand Overture",
            "startCN": 1728446400
        },
        "act1vecb": {
            "nameCN": "矢量突破",
            "nameEN": "Vector Breakthrough",
            "startCN": 1727424000
        },
        "act28sre": {
            "nameCN": "不义之财 复刻",
            "nameEN": "Come Catastrophes or Wakes of Vultures - Rerun",
            "startCN": 1726732800
        },
        "act36side": {
            "nameCN": "泰拉饭",
            "nameEN": "Delicious On Terra",
            "startCN": 1725249600
        },
        "act27sre": {
            "nameCN": "火山旅梦·复刻",
            "nameEN": "So Long, Adele: Home Away From Home - Retrospection",
            "startCN": 1724313600
        },
        "act35side": {
            "nameCN": "太阳甩在身后",
            "nameEN": "Adventure That Cannot Wait for the Sun",
            "startCN": 1722484800
        },
        "act17mini": {
            "nameCN": "熔炉“还魂”记",
            "nameEN": "A Kazdelian Rescue",
            "startCN": 1720497600
        },
        "act26sre": {
            "nameCN": "空想花庭·复刻",
            "nameEN": "Hortus de Escapismo - Retrospection",
            "startCN": 1719302400
        },
        "act34side": {
            "nameCN": "生路",
            "nameEN": "Path of Life",
            "startCN": 1717560000
        },
        "act25sre": {
            "nameCN": "孤星·复刻",
            "nameEN": "Lone Trail - Rerun",
            "startCN": 1716537600
        },
        "act2vmulti": {
            "nameCN": "罗德岛促融共竞",
            "nameEN": "Rhodes Island Icebreaker Games",
            "startCN": 1715760000
        },
        "act33side": {
            "nameCN": "巴别塔",
            "nameEN": "Babel",
            "startCN": 1712808000
        },
        "act32side": {
            "nameCN": "水晶箭行动",
            "nameEN": "Operation Lucent Arrowhead",
            "startCN": 1709784000
        },
        "act1r6sre": {
            "nameCN": "源石尘行动·复刻",
            "nameEN": "Operation Originium Dust - Retrospection",
            "startCN": 1711008000
        },
        "act4bossrush": {
            "nameCN": "引航者试炼",
            "nameEN": "Trials for Navigator #4",
            "startCN": 1708588800
        },
        "act31side": {
            "nameCN": "怀黍离",
            "nameEN": "Here A People Sows",
            "startCN": 1706760000
        },
        "act23sre": {
            "nameCN": "登临意·复刻",
            "nameEN": "Where Vernal Winds Will Never Blow - Rerun",
            "startCN": 1705564800
        },
        "act16mini": {
            "nameCN": "去咧嘴谷",
            "nameEN": "To the Grinning Valley",
            "startCN": 1704787200
        },
        "act22sre": {
            "nameCN": "照我以火·复刻",
            "nameEN": "What the Firelight Casts - Retrospection",
            "startCN": 1703232000
        },
        "act30side": {
            "nameCN": "银心湖列车",
            "nameEN": "The Rides to Lake Silberneherze",
            "startCN": 1701748800
        },
        "act29side": {
            "nameCN": "崔林特尔梅之金",
            "nameEN": "Zwillingstürme im Herbst",
            "startCN": 1698811200
        },
        "act21sre": {
            "nameCN": "叙拉古人·复刻",
            "nameEN": "Il Siracusano - Retrospection",
            "startCN": 1697961600
        },
        "act42d0": {
            "nameCN": "纷争演绎",
            "nameEN": "DOS : Design of Strife",
            "startCN": 1695801600
        },
        "act28side": {
            "nameCN": "不义之财",
            "nameEN": "Come Catastrophes or Wakes of Vultures",
            "startCN": 1693886400
        },
        "act20sre": {
            "nameCN": "理想城：长夏狂欢季·复刻",
            "nameEN": "Ideal City: Endless Carnival - Rerun",
            "startCN": 1693468800
        },
        "act3bossrush": {
            "nameCN": "引航者试炼",
            "nameEN": "Trials for Navigator #3",
            "startCN": 1692345600
        },
        "act27side": {
            "nameCN": "火山旅梦",
            "nameEN": "So Long, Adele: Home Away From Home",
            "startCN": 1690862400
        },
        "act19sre": {
            "nameCN": "绿野幻梦·复刻",
            "nameEN": "Dorothy's Vision - Retrospection",
            "startCN": 1689667200
        },
        "act15mini": {
            "nameCN": "眠于树影之中",
            "nameEN": "The Black Forest Wills A Dream",
            "startCN": 1688616000
        },
        "act26side": {
            "nameCN": "空想花庭",
            "nameEN": "Hortus de Escapismo",
            "startCN": 1686196800
        },
        "act18sre": {
            "nameCN": "尘影余音·复刻",
            "nameEN": "Lingering Echoes - Rerun",
            "startCN": 1687248000
        },
        "act38d1": {
            "nameCN": "尖灭测试作战",
            "nameEN": "Pinch-Out Experimental Operation",
            "startCN": 1684742400
        },
        "act25side": {
            "nameCN": "孤星",
            "nameEN": "Lone Trail",
            "startCN": 1682913600
        },
        "act17sre": {
            "nameCN": "愚人号·复刻",
            "nameEN": "Stultifera Navis - Rerun",
            "startCN": 1681977600
        },
        "act24side": {
            "nameCN": "落叶逐火",
            "nameEN": "A Flurry to the Flame",
            "startCN": 1678161600
        },
        "act1sandbox": {
            "nameCN": "生息演算：沙中之火",
            "nameEN": "Reclamation Algorithm - Fire Within the Sand",
            "startCN": 1674979200
        },
        "act16sre": {
            "nameCN": "吾导先路·复刻",
            "nameEN": "Guide Ahead - Rerun",
            "startCN": 1676966400
        },
        "act14mini": {
            "nameCN": "春分",
            "nameEN": "A Death in Chunfen",
            "startCN": 1676361600
        },
        "act23side": {
            "nameCN": "登临意",
            "nameEN": "Where Vernal Winds Will Never Blow",
            "startCN": 1673928000
        },
        "act15sre": {
            "nameCN": "将进酒·复刻",
            "nameEN": "Invitation to Wine - Rerun",
            "startCN": 1672560000
        },
        "act22side": {
            "nameCN": "照我以火",
            "nameEN": "What the Firelight Casts",
            "startCN": 1671076800
        },
        "act2bossrush": {
            "nameCN": "引航者试炼",
            "nameEN": "Trials for Navigator #2",
            "startCN": 1673337600
        },
        "act21side": {
            "nameCN": "叙拉古人",
            "nameEN": "IL Siracusano",
            "startCN": 1667275200
        },
        "act14sre": {
            "nameCN": "风雪过境·复刻",
            "nameEN": "Break the Ice - Rerun",
            "startCN": 1669881600
        },
        "act13sre": {
            "nameCN": "长夜临光·复刻",
            "nameEN": "Near Light - Rerun",
            "startCN": 1663833600
        },
        "act13mini": {
            "nameCN": "好久不见",
            "nameEN": "It's Been a While",
            "startCN": 1663228800
        },
        "act12mini": {
            "nameCN": "日暮寻路",
            "nameEN": "An Obscure Wanderer",
            "startCN": 1662609600
        },
        "act20side": {
            "nameCN": "理想城：长夏狂欢季",
            "nameEN": "Ideal City: Endless Carnival",
            "startCN": 1660190400
        },
        "act1bossrush": {
            "nameCN": "引航者试炼",
            "nameEN": "Trials for Navigator #1",
            "startCN": 1660809600
        },
        "act12sre": {
            "nameCN": "多索雷斯假日·复刻",
            "nameEN": "Dossoles Holiday",
            "startCN": 1658822400
        },
        "act11mini": {
            "nameCN": "未尽篇章",
            "nameEN": "To Be Continued",
            "startCN": 1658217600
        },
        "act19side": {
            "nameCN": "绿野幻梦",
            "nameEN": "Dorothy's Vision",
            "startCN": 1656993600
        },
        "act18side": {
            "nameCN": "尘影余音",
            "nameEN": "Lingering Echoes",
            "startCN": 1654747200
        },
        "act11sre": {
            "nameCN": "覆潮之下·复刻",
            "nameEN": "Under Tides - Rerun",
            "startCN": 1653897600
        },
        "act17side": {
            "nameCN": "愚人号",
            "nameEN": "Stultifera Navis",
            "startCN": 1651388400
        },
        "act10sre": {
            "nameCN": "遗尘漫步·复刻",
            "nameEN": "A Walk in the Dust - Rerun",
            "startCN": 1648540800
        },
        "act16side": {
            "nameCN": "吾导先路",
            "nameEN": "Guide Ahead",
            "startCN": 1647316800
        },
        "act10mini": {
            "nameCN": "阴云火花",
            "nameEN": "A Light Spark in Darkness",
            "startCN": 1644912000
        },
        "act15side": {
            "nameCN": "将进酒",
            "nameEN": "Invitation to Wine",
            "startCN": 1643083200
        },
        "act9sre": {
            "nameCN": "画中人·复刻",
            "nameEN": "Who Is Real - Rerun",
            "startCN": 1641801600
        },
        "act14side": {
            "nameCN": "风雪过境",
            "nameEN": "Break the Ice",
            "startCN": 1640059200
        },
        "act8sre": {
            "nameCN": "孤岛风云·复刻",
            "nameEN": "Mansfield Break - Rerun",
            "startCN": 1638864000
        },
        "act13side": {
            "nameCN": "长夜临光",
            "nameEN": "Near Light",
            "startCN": 1635739200
        },
        "act9mini": {
            "nameCN": "红松林",
            "nameEN": "Pinus Sylvestris",
            "startCN": 1634284800
        },
        "act7sre": {
            "nameCN": "玛莉娅·临光·复刻",
            "nameEN": "Maria Nearl - Rerun",
            "startCN": 1633075200
        },
        "act12side": {
            "nameCN": "多索雷斯假日",
            "nameEN": "Dossoles Holiday",
            "startCN": 1627963200
        },
        "act6sre": {
            "nameCN": "密林悍将归来·复刻",
            "nameEN": "The Great Chief Returns - Rerun",
            "startCN": 1626768000
        },
        "act8mini": {
            "nameCN": "如我所见",
            "nameEN": "Vigilo",
            "startCN": 1626163200
        },
        "act1lock": {
            "nameCN": "荷谟伊智境",
            "nameEN": "Hymnoi Wisdom",
            "startCN": 1625198400
        },
        "act5sre": {
            "nameCN": "沃伦姆德的薄暮·复刻",
            "nameEN": "Twilight of Wolumonde - Rerun",
            "startCN": 1623916800
        },
        "act7mini": {
            "nameCN": "灯火序曲",
            "nameEN": "Preluding Lights",
            "startCN": 1622520000
        },
        "act18d3": {
            "nameCN": "覆潮之下",
            "nameEN": "Under Tides",
            "startCN": 1619852400
        },
        "act18d0": {
            "nameCN": "遗尘漫步",
            "nameEN": "A Walk in the Dust",
            "startCN": 1618459200
        },
        "act17d5": {
            "nameCN": "生于黑夜·复刻",
            "nameEN": "Darknights Memoir - Rerun",
            "startCN": 1617091200
        },
        "act17d1": {
            "nameCN": "罗德岛防御协议",
            "nameEN": "Defense Protocols",
            "startCN": 1612324800
        },
        "act17d0": {
            "nameCN": "源石尘行动",
            "nameEN": "Operation Originium Dust",
            "startCN": 1612324800
        },
        "act16d5": {
            "nameCN": "画中人",
            "nameEN": "Who Is Real",
            "startCN": 1612512000
        },
        "act15d5": {
            "nameCN": "此地之外",
            "nameEN": "Beyond Here",
            "startCN": 1609833600
        },
        "act15d0": {
            "nameCN": "孤岛风云",
            "nameEN": "Mansfield Break",
            "startCN": 1608177600
        },
        "act14d7": {
            "nameCN": "喧闹法则·复刻",
            "nameEN": "Code of Brawl - Rerun",
            "startCN": 1606809600
        },
        "act13d5": {
            "nameCN": "玛莉娅·临光",
            "nameEN": "Maria Nearl",
            "startCN": 1602748800
        },
        "act13d2": {
            "nameCN": "骑兵与猎人·复刻",
            "nameEN": "Grani and the Knights' Treasure - Rerun",
            "startCN": 1601539200
        },
        "act13d0": {
            "nameCN": "踏寻往昔之风",
            "nameEN": "Rewinding Breeze",
            "startCN": 1600920000
        },
        "act12d6": {
            "nameCN": "刻俄柏的灰蕈迷境",
            "nameEN": "Ceobe's Fungimist",
            "startCN": 1598328000
        },
        "act12d0": {
            "nameCN": "密林悍将归来",
            "nameEN": "The Great Chief Returns",
            "startCN": 1598328000
        },
        "act11d7": {
            "nameCN": "火蓝之心·复刻",
            "nameEN": "Heart of Surging Flame - Rerun",
            "startCN": 1597132800
        },
        "act11d0": {
            "nameCN": "沃伦姆德的薄暮",
            "nameEN": "Twilight of Wolumonde",
            "startCN": 1594267200
        },
        "act10d5": {
            "nameCN": "乌萨斯的孩子们",
            "nameEN": "Children of Ursus",
            "startCN": 1592467200
        },
        "act9d0": {
            "nameCN": "生于黑夜",
            "nameEN": "Darknights Memoir",
            "startCN": 1587441600
        },
        "act7d5": {
            "nameCN": "午间逸话",
            "nameEN": "Stories of Afternoon",
            "startCN": 1582617600
        },
        "act6d5": {
            "nameCN": "洪炉示岁",
            "nameEN": "Ancient Forge",
            "startCN": 1578513600
        },
        "act5d1": {
            "nameCN": "危机合约",
            "nameEN": "Contingency Contract",
            "startCN": 1574150400
        },
        "act5d0": {
            "nameCN": "喧闹法则",
            "nameEN": "Code of Brawl",
            "startCN": 1574150400
        },
        "act4d0": {
            "nameCN": "战地秘闻",
            "nameEN": "Operational Intelligence",
            "startCN": 1571126400
        },
        "act3d0": {
            "nameCN": "火蓝之心",
            "nameEN": "Heart of Surging Flame",
            "startCN": 1566892800
        },
        "1stact": {
            "nameCN": "骑兵与猎人",
            "nameEN": "Grani and the Knights' Treasure",
            "startCN": 1559181600
        },
        "main_0": {
            "nameCN": "Episode 00 : 黑暗时代·上",
            "nameEN": "Episode 00 : Evil Time Part 1",
            "startCN": -1
        },
        "main_1": {
            "nameCN": "Episode 01 : 黑暗时代·下",
            "nameEN": "Episode 01 : Evil Time Part 2",
            "startCN": -1
        },
        "main_2": {
            "nameCN": "Episode 02 : 异卵同生",
            "nameEN": "Episode 02 : Separated Hearts",
            "startCN": -1
        },
        "main_3": {
            "nameCN": "Episode 03 : 二次呼吸",
            "nameEN": "Episode 03 : Stinging Shock",
            "startCN": -1
        },
        "main_4": {
            "nameCN": "Episode 04 : 急性衰竭",
            "nameEN": "Episode 04 : Burning Run",
            "startCN": -1
        },
        "main_5": {
            "nameCN": "Episode 05 : 靶向药物",
            "nameEN": "Episode 05 : Necessary Solutions",
            "startCN": -1
        },
        "main_6": {
            "nameCN": "Episode 06 : 局部坏死",
            "nameEN": "Episode 06 : Partial Necrosis",
            "startCN": -1
        },
        "main_7": {
            "nameCN": "Episode 07 : 苦难摇篮",
            "nameEN": "Episode 07 : The Birth of Tragedy",
            "startCN": -1
        },
        "main_8": {
            "nameCN": "Episode 08 : 怒号光明",
            "nameEN": "Episode 08 : Roaring Flare",
            "startCN": -1
        },
        "main_9": {
            "nameCN": "Episode 09 : 风暴瞭望",
            "nameEN": "Episode 09 : Stormwatch",
            "startCN": -1
        },
        "main_10": {
            "nameCN": "Episode 10 : 破碎日冕",
            "nameEN": "Episode 10 : Shatterpoint",
            "startCN": 1649908800
        },
        "main_11": {
            "nameCN": "Episode 11 : 淬火尘霾",
            "nameEN": "Episode 11 : Return To Mist",
            "startCN": 1665475200
        },
        "main_12": {
            "nameCN": "Episode 12 : 惊霆无声",
            "nameEN": "Episode 12 : All Quiet Under the Thunder",
            "startCN": 1680753600
        },
        "main_13": {
            "nameCN": "Episode 13 : 恶兆湍流",
            "nameEN": "Episode 13 : The Whirlpool that is Passion",
            "startCN": 1696737600
        },
        "main_14": {
            "nameCN": "Episode 14 : 慈悲灯塔",
            "nameEN": "Episode 14 : Absolved Will Be the Seekers",
            "startCN": 1714536000
        },
        "weekly_9": {
            "nameCN": "货物运送 (wk_melee)",
            "nameEN": "CE : Cargo Escort (LMD)",
            "startCN": -1
        },
        "weekly_8": {
            "nameCN": "资源保障 (wk_armor)",
            "nameEN": "SK : Resource Search (Building materials)",
            "startCN": -1
        },
        "weekly_7": {
            "nameCN": "战术演习 (wk_kc)",
            "nameEN": "LS : Tactical Drill (Battle Record)",
            "startCN": -1
        },
        "weekly_5": {
            "nameCN": "粉碎防御 (wk_toxic)",
            "nameEN": "AP : Tough Siege (Purchase Certificate)",
            "startCN": -1
        },
        "weekly_6": {
            "nameCN": "空中威胁 (wk_fly)",
            "nameEN": "CA : Aerial Threat (Skill Summary)",
            "startCN": -1
        },
        "weekly_1": {
            "nameCN": "固若金汤 (pro_a)",
            "nameEN": "PR-A : Solid Defense (Defenders & Medics)",
            "startCN": -1
        },
        "weekly_2": {
            "nameCN": "摧枯拉朽 (pro_b)",
            "nameEN": "PR-B : Fierce Attack (Snipers & Casters)",
            "startCN": -1
        },
        "weekly_3": {
            "nameCN": "势不可挡 (pro_c)",
            "nameEN": "PR-C : Unstoppable Charge (Vanguards & Supporters)",
            "startCN": -1
        },
        "weekly_4": {
            "nameCN": "身先士卒 (pro_d)",
            "nameEN": "PR-D : Fearless Protection (Guards & Specialists)",
            "startCN": -1
        },
        "act17d7": {
            "nameCN": "愚人节活动",
            "nameEN": "April Fools' Day Event 2021 (EN : 2022)",
            "startCN": 1617264000
        },
        "camp_01": {
            "nameCN": "切尔诺伯格",
            "nameEN": "Chernobog",
            "startCN": -1
        },
        "camp_02": {
            "nameCN": "龙门外环",
            "nameEN": "Lungmen Outskirts",
            "startCN": -1
        },
        "camp_03": {
            "nameCN": "龙门市区",
            "nameEN": "Lungmen Downtown",
            "startCN": -1
        },
        "camp_r_01": {
            "nameCN": "大骑士领郊外",
            "nameEN": "The Grand Knight Territory Outskirts",
            "startCN": 1604260800
        },
        "camp_r_02": {
            "nameCN": "北原冰封废城",
            "nameEN": "Frozen Abandoned City",
            "startCN": 1609704000
        },
        "camp_r_03": {
            "nameCN": "废弃矿区",
            "nameEN": "Abandoned Mine",
            "startCN": 1615147200
        },
        "camp_r_04": {
            "nameCN": "潮没海滨",
            "nameEN": "Flooded Seashore",
            "startCN": 1619985600
        },
        "camp_r_05": {
            "nameCN": "积水潮窟",
            "nameEN": "Watery Tidehollow",
            "startCN": 1626033600
        },
        "camp_r_06": {
            "nameCN": "长泉镇郊野",
            "nameEN": "Long Spring Wastes",
            "startCN": 1630872000
        },
        "camp_r_07": {
            "nameCN": "多索雷斯换水口",
            "nameEN": "Dossoles Water Gate",
            "startCN": 1635710400
        },
        "camp_r_08": {
            "nameCN": "南方监狱",
            "nameEN": "South Prison",
            "startCN": 1641758400
        },
        "camp_r_09": {
            "nameCN": "小丘郡郊野",
            "nameEN": "County Hillock Countryside",
            "startCN": 1646596800
        },
        "camp_r_10": {
            "nameCN": "黑夜锦标秀",
            "nameEN": "Night Champion Show",
            "startCN": 1651435200
        },
        "camp_r_11": {
            "nameCN": "盘桓蜀道",
            "nameEN": "Lingering Shangshu Trails",
            "startCN": 1657483200
        },
        "camp_r_12": {
            "nameCN": "巧克力大街",
            "nameEN": "Chocolate Street",
            "startCN": 1662321600
        },
        "camp_r_13": {
            "nameCN": "昏黑造船厂",
            "nameEN": "Penumbra Shipyards",
            "startCN": 1667160000
        },
        "camp_r_14": {
            "nameCN": "实验基地机库",
            "nameEN": "Research Base Hanger",
            "startCN": 1673208000
        },
        "camp_r_15": {
            "nameCN": "龙门商业街",
            "nameEN": "Lungmen Commercial District",
            "startCN": 1678046400
        },
        "camp_r_16": {
            "nameCN": "休止符街道",
            "nameEN": "Rest Avenue",
            "startCN": 1682884800
        },
        "camp_r_17": {
            "nameCN": "灰暗泥沼",
            "nameEN": "Ashy Marsh",
            "startCN": 1688932800
        },
        "camp_r_18": {
            "nameCN": "“特制小水坑”",
            "nameEN": "The Special Little Aquapit'",
            "startCN": 1693771200
        },
        "camp_r_19": {
            "nameCN": "腐烂荒野",
            "nameEN": "Decaying Wastes",
            "startCN": 1698609600
        },
        "camp_r_20": {
            "nameCN": "千嶂边城",
            "nameEN": "Mountain-Ringed Border Town",
            "startCN": 1704657600
        },
        "camp_r_21": {
            "nameCN": "新旅店大道",
            "nameEN": "New Hotel Avenue",
            "startCN": 1709496000
        },
        "camp_r_22": {
            "nameCN": "“离心率”实验室",
            "nameEN": "'Eccentricity' Laboratory",
            "startCN": 1714334400
        },
        "camp_r_23": {
            "nameCN": "燃烧街区",
            "nameEN": "Burning District",
            "startCN": 1720382400
        },
        "camp_r_24": {
            "nameCN": "冰封雪谷",
            "nameEN": "Icebound Valley",
            "startCN": 1725220800
        },
        "camp_r_25": {
            "nameCN": "66号航道",
            "nameEN": "Cityway 66",
            "startCN": 1730059200
        },
        "camp_r_26": {
            "nameCN": "壬午号水稻田",
            "nameEN": "Paddy Field 9-7",
            "startCN": 1736107200
        },
        "camp_r_27": {
            "nameCN": "选帝侯广场",
            "nameEN": "Kurfürstenplatz",
            "startCN": 1740945600
        },
        "camp_r_28": {
            "nameCN": "大巴扎",
            "nameEN": "大巴扎",
            "startCN": 1745784000
        },
        "camp_r_29": {
            "nameCN": "鳞骸盐漠 ",
            "nameEN": "鳞骸盐漠 ",
            "startCN": 1753646400
        },
        "tower_tr_01": {
            "nameCN": "7号训练场",
            "nameEN": "Training Ground #7",
            "startCN": -1
        },
        "tower_tr_02": {
            "nameCN": "9号训练场",
            "nameEN": "Training Ground #9",
            "startCN": -1
        },
        "tower_tr_03": {
            "nameCN": "10号训练场",
            "nameEN": "Training Ground #10",
            "startCN": -1
        },
        "tower_n_05": {
            "nameCN": "多索雷斯在建地块",
            "nameEN": "Under-Construction Dossoles Plate",
            "startCN": -1
        },
        "tower_n_06": {
            "nameCN": "阿卡胡拉丛林",
            "nameEN": "Acahuallan Jungle",
            "startCN": -1
        },
        "tower_n_07": {
            "nameCN": "约翰老妈新建地块",
            "nameEN": "Mama John's New Plate",
            "startCN": -1
        },
        "tower_n_08": {
            "nameCN": "雷神工业测试平台 ",
            "nameEN": "Raythean Industries Test Platform",
            "startCN": -1
        },
        "tower_n_09": {
            "nameCN": "阿尔斯特甜品制作平台",
            "nameEN": "Alsterii Bellariorum Manufacture Platform",
            "startCN": -1
        },
        "tower_n_10": {
            "nameCN": "荒废灯塔",
            "nameEN": "The Abandoned Lighthouse",
            "startCN": -1
        },
        "tower_n_11": {
            "nameCN": "塔山农业实验平台",
            "nameEN": "Tower Mountains Agricultural Experimental Platform",
            "startCN": -1
        },
        "tower_n_12": {
            "nameCN": "自走机械搏斗场",
            "nameEN": "Automaton Arena",
            "startCN": -1
        },
        "tower_n_13": {
            "nameCN": "边地移动城镇",
            "nameEN": "Nomadic Border Town",
            "startCN": -1
        },
        "tower_n_14": {
            "nameCN": "多索雷斯商业地块",
            "nameEN": "Dossoles Commercial Plate",
            "startCN": -1
        },
        "tower_n_15": {
            "nameCN": "交战荒野",
            "nameEN": "War-torn Wilderness",
            "startCN": -1
        },
        "tower_n_16": {
            "nameCN": "玉门市集",
            "nameEN": "Yumen Market",
            "startCN": -1
        },
        "tower_n_17": {
            "nameCN": "荒地群兽音乐厅",
            "nameEN": "Barren Beasts Concert Hall",
            "startCN": -1
        },
        "tower_n_18": {
            "nameCN": "尚蜀夜市",
            "nameEN": "尚蜀夜市",
            "startCN": -1
        },
        "tower_n_19": {
            "nameCN": "艺术馆旧址",
            "nameEN": "艺术馆旧址",
            "startCN": -1
        },
        "tower_n_01": {
            "nameCN": "钢铁萝卜矿场",
            "nameEN": "Iron Carrot Mine",
            "startCN": -1
        },
        "tower_n_02": {
            "nameCN": "多伦矿场",
            "nameEN": "Toron Mine",
            "startCN": -1
        },
        "tower_n_03": {
            "nameCN": "格里布采矿平台",
            "nameEN": "Glebe Mining Platform",
            "startCN": -1
        },
        "tower_n_04": {
            "nameCN": "斯沃玛加工平台",
            "nameEN": "Słoma Processing Platform",
            "startCN": -1
        },
        "Mechanic": {
            "nameCN": "训练场",
            "nameEN": "Training Ground",
            "startCN": 1722484800
        },
        "CC#Beta": {
            "nameCN": "危机合约",
            "nameEN": "CC#Beta : Contingency Contract",
            "startCN": 1574150400
        },
        "CC#00": {
            "nameCN": "荒芜行动",
            "nameEN": "CC#00 : Operation Barrenland",
            "startCN": 1584417600
        },
        "CC#01": {
            "nameCN": "黄铁行动",
            "nameEN": "CC#01 : Operation Pyrite",
            "startCN": 1591070400
        },
        "CC#02": {
            "nameCN": "利刃行动",
            "nameEN": "CC#02 : Operation Blade",
            "startCN": 1595923200
        },
        "CC#03": {
            "nameCN": "燃灰行动",
            "nameEN": "CC#03 : Operation Cinder",
            "startCN": 1605427200
        },
        "CC#04": {
            "nameCN": "铅封行动",
            "nameEN": "CC#04 : Operation Lead Seal",
            "startCN": 1611028800
        },
        "CC#05": {
            "nameCN": "光谱行动",
            "nameEN": "CC#05 : Operation Spectrum",
            "startCN": 1621065600
        },
        "CC#06": {
            "nameCN": "蛮鳞行动",
            "nameEN": "CC#06 : Operation Wild Scales",
            "startCN": 1629964800
        },
        "CC#07": {
            "nameCN": "松烟行动",
            "nameEN": "CC#07 : Operation Pine Soot",
            "startCN": 1637568000
        },
        "CC#08": {
            "nameCN": "寻昼行动",
            "nameEN": "CC#08 : Operation Dawnseeker",
            "startCN": 1645689600
        },
        "CC#09": {
            "nameCN": "渊默行动",
            "nameEN": "CC#09 : Operation Deepness",
            "startCN": 1652947200
        },
        "CC#10": {
            "nameCN": "尘环行动",
            "nameEN": "CC#10 : Operation Ashring",
            "startCN": 1661414400
        },
        "CC#11": {
            "nameCN": "赝波行动",
            "nameEN": "CC#11 : Operation Fake Waves",
            "startCN": 1668499200
        },
        "CC#12": {
            "nameCN": "起源行动",
            "nameEN": "CC#12 : Operation Basepoint",
            "startCN": 1679385600
        },
        "PinchOut": {
            "nameCN": "尖灭测试作战",
            "nameEN": "Pinch-Out Experimental Operation",
            "startCN": 1684742400
        },
        "CCBP#01": {
            "nameCN": "浊燃作战",
            "nameEN": "CCBP#01 : Battleplan Pyrolysis",
            "startCN": 1700553600
        },
        "CCBP#02": {
            "nameCN": "潮曦作战",
            "nameEN": "CCBP#02 : Battleplan Underdawn",
            "startCN": 1711612800
        },
        "CCBP#03": {
            "nameCN": "净罪作战",
            "nameEN": "CCBP#03 : Battleplan Extinguished Sins",
            "startCN": 1738742400
        },
        "CCBP#04": {
            "nameCN": "弧光作战",
            "nameEN": "CCBP#04 : Battleplan Arclight",
            "startCN": 1755158400
        },
        "IS#1": {
            "nameCN": "刻俄柏的灰蕈迷境",
            "nameEN": "IS#1 : Ceobe's Fungimist",
            "startCN": 1598328000
        },
        "IS#2": {
            "nameCN": "傀影与猩红孤钻",
            "nameEN": "IS#2 : Phantom & Crimson Solitaire",
            "startCN": 1641369600
        },
        "IS#3": {
            "nameCN": "水月与深蓝之树",
            "nameEN": "IS#3 : Mizuki & Caerula Arbor",
            "startCN": 1664251200
        },
        "IS#4": {
            "nameCN": "探索者的银凇止境",
            "nameEN": "IS#4 : Expeditioner's Jǫklumarkar",
            "startCN": 1689235200
        },
        "IS#5": {
            "nameCN": "萨卡兹的无终奇语",
            "nameEN": "IS#5 : Sarkaz's Furnaceside Fables",
            "startCN": 1721116800
        },
        "IS#6": {
            "nameCN": "岁的界园志异",
            "nameEN": "IS#6 : Sui's Garden of Grotesqueries",
            "startCN": 1752566400
        },
        "RA#1": {
            "nameCN": "生息演算：沙中之火",
            "nameEN": "RA#1 : Reclamation Algorithm - Fire Within the Sand",
            "startCN": 1674979200
        },
        "RA#2": {
            "nameCN": "沙洲遗闻",
            "nameEN": "RA#2 : Reclamation Algorithm - Tales Within the Sand",
            "startCN": 1706929200
        },
        "act3fun": {
            "nameCN": "愚人节活动",
            "nameEN": "April Fools' Day Event 2022 (EN : 2023)",
            "startCN": 1648800000
        },
        "act4fun": {
            "nameCN": "愚人节活动",
            "nameEN": "April Fools' Day Event 2023 (EN : 2024)",
            "startCN": 1680336000
        },
        "act5fun": {
            "nameCN": "愚人节活动",
            "nameEN": "April Fools' Day Event 2024 (EN : 2025)",
            "startCN": 1711958400
        },
        "act6fun": {
            "nameCN": "愚人节活动",
            "nameEN": "April Fools' Day Event 2025 (EN : 2026)",
            "startCN": 1743494400
        }
    },
    "Timeline": [
        [
            "1stact",
            "Grani and the Knights' Treasure",
            1559181600
        ],
        [
            "act3d0",
            "Heart of Surging Flame",
            1566892800
        ],
        [
            "act4d0",
            "Operational Intelligence",
            1571126400
        ],
        [
            "act5d1",
            "Contingency Contract",
            1574150400
        ],
        [
            "act5d0",
            "Code of Brawl",
            1574150400
        ],
        [
            "CC#Beta",
            "CC#Beta : Contingency Contract",
            1574150400
        ],
        [
            "act6d5",
            "Ancient Forge",
            1578513600
        ],
        [
            "act7d5",
            "Stories of Afternoon",
            1582617600
        ],
        [
            "CC#00",
            "CC#00 : Operation Barrenland",
            1584417600
        ],
        [
            "act9d0",
            "Darknights Memoir",
            1587441600
        ],
        [
            "CC#01",
            "CC#01 : Operation Pyrite",
            1591070400
        ],
        [
            "act10d5",
            "Children of Ursus",
            1592467200
        ],
        [
            "act11d0",
            "Twilight of Wolumonde",
            1594267200
        ],
        [
            "CC#02",
            "CC#02 : Operation Blade",
            1595923200
        ],
        [
            "act11d7",
            "Heart of Surging Flame - Rerun",
            1597132800
        ],
        [
            "act12d6",
            "Ceobe's Fungimist",
            1598328000
        ],
        [
            "act12d0",
            "The Great Chief Returns",
            1598328000
        ],
        [
            "IS#1",
            "IS#1 : Ceobe's Fungimist",
            1598328000
        ],
        [
            "act13d0",
            "Rewinding Breeze",
            1600920000
        ],
        [
            "act13d2",
            "Grani and the Knights' Treasure - Rerun",
            1601539200
        ],
        [
            "act13d5",
            "Maria Nearl",
            1602748800
        ],
        [
            "camp_r_01",
            "The Grand Knight Territory Outskirts",
            1604260800
        ],
        [
            "CC#03",
            "CC#03 : Operation Cinder",
            1605427200
        ],
        [
            "act14d7",
            "Code of Brawl - Rerun",
            1606809600
        ],
        [
            "act15d0",
            "Mansfield Break",
            1608177600
        ],
        [
            "camp_r_02",
            "Frozen Abandoned City",
            1609704000
        ],
        [
            "act15d5",
            "Beyond Here",
            1609833600
        ],
        [
            "CC#04",
            "CC#04 : Operation Lead Seal",
            1611028800
        ],
        [
            "act17d1",
            "Defense Protocols",
            1612324800
        ],
        [
            "act17d0",
            "Operation Originium Dust",
            1612324800
        ],
        [
            "act16d5",
            "Who Is Real",
            1612512000
        ],
        [
            "camp_r_03",
            "Abandoned Mine",
            1615147200
        ],
        [
            "act17d5",
            "Darknights Memoir - Rerun",
            1617091200
        ],
        [
            "act17d7",
            "April Fools' Day Event 2021 (EN : 2022)",
            1617264000
        ],
        [
            "act18d0",
            "A Walk in the Dust",
            1618459200
        ],
        [
            "act18d3",
            "Under Tides",
            1619852400
        ],
        [
            "camp_r_04",
            "Flooded Seashore",
            1619985600
        ],
        [
            "CC#05",
            "CC#05 : Operation Spectrum",
            1621065600
        ],
        [
            "act7mini",
            "Preluding Lights",
            1622520000
        ],
        [
            "act5sre",
            "Twilight of Wolumonde - Rerun",
            1623916800
        ],
        [
            "act1lock",
            "Hymnoi Wisdom",
            1625198400
        ],
        [
            "camp_r_05",
            "Watery Tidehollow",
            1626033600
        ],
        [
            "act8mini",
            "Vigilo",
            1626163200
        ],
        [
            "act6sre",
            "The Great Chief Returns - Rerun",
            1626768000
        ],
        [
            "act12side",
            "Dossoles Holiday",
            1627963200
        ],
        [
            "CC#06",
            "CC#06 : Operation Wild Scales",
            1629964800
        ],
        [
            "camp_r_06",
            "Long Spring Wastes",
            1630872000
        ],
        [
            "act7sre",
            "Maria Nearl - Rerun",
            1633075200
        ],
        [
            "act9mini",
            "Pinus Sylvestris",
            1634284800
        ],
        [
            "camp_r_07",
            "Dossoles Water Gate",
            1635710400
        ],
        [
            "act13side",
            "Near Light",
            1635739200
        ],
        [
            "CC#07",
            "CC#07 : Operation Pine Soot",
            1637568000
        ],
        [
            "act8sre",
            "Mansfield Break - Rerun",
            1638864000
        ],
        [
            "act14side",
            "Break the Ice",
            1640059200
        ],
        [
            "IS#2",
            "IS#2 : Phantom & Crimson Solitaire",
            1641369600
        ],
        [
            "camp_r_08",
            "South Prison",
            1641758400
        ],
        [
            "act9sre",
            "Who Is Real - Rerun",
            1641801600
        ],
        [
            "act15side",
            "Invitation to Wine",
            1643083200
        ],
        [
            "act10mini",
            "A Light Spark in Darkness",
            1644912000
        ],
        [
            "CC#08",
            "CC#08 : Operation Dawnseeker",
            1645689600
        ],
        [
            "camp_r_09",
            "County Hillock Countryside",
            1646596800
        ],
        [
            "act16side",
            "Guide Ahead",
            1647316800
        ],
        [
            "act10sre",
            "A Walk in the Dust - Rerun",
            1648540800
        ],
        [
            "act3fun",
            "April Fools' Day Event 2022 (EN : 2023)",
            1648800000
        ],
        [
            "main_10",
            "Episode 10 : Shatterpoint",
            1649908800
        ],
        [
            "act17side",
            "Stultifera Navis",
            1651388400
        ],
        [
            "camp_r_10",
            "Night Champion Show",
            1651435200
        ],
        [
            "CC#09",
            "CC#09 : Operation Deepness",
            1652947200
        ],
        [
            "act11sre",
            "Under Tides - Rerun",
            1653897600
        ],
        [
            "act18side",
            "Lingering Echoes",
            1654747200
        ],
        [
            "act19side",
            "Dorothy's Vision",
            1656993600
        ],
        [
            "camp_r_11",
            "Lingering Shangshu Trails",
            1657483200
        ],
        [
            "act11mini",
            "To Be Continued",
            1658217600
        ],
        [
            "act12sre",
            "Dossoles Holiday",
            1658822400
        ],
        [
            "act20side",
            "Ideal City: Endless Carnival",
            1660190400
        ],
        [
            "act1bossrush",
            "Trials for Navigator #1",
            1660809600
        ],
        [
            "CC#10",
            "CC#10 : Operation Ashring",
            1661414400
        ],
        [
            "camp_r_12",
            "Chocolate Street",
            1662321600
        ],
        [
            "act12mini",
            "An Obscure Wanderer",
            1662609600
        ],
        [
            "act13mini",
            "It's Been a While",
            1663228800
        ],
        [
            "act13sre",
            "Near Light - Rerun",
            1663833600
        ],
        [
            "IS#3",
            "IS#3 : Mizuki & Caerula Arbor",
            1664251200
        ],
        [
            "main_11",
            "Episode 11 : Return To Mist",
            1665475200
        ],
        [
            "camp_r_13",
            "Penumbra Shipyards",
            1667160000
        ],
        [
            "act21side",
            "IL Siracusano",
            1667275200
        ],
        [
            "CC#11",
            "CC#11 : Operation Fake Waves",
            1668499200
        ],
        [
            "act14sre",
            "Break the Ice - Rerun",
            1669881600
        ],
        [
            "act22side",
            "What the Firelight Casts",
            1671076800
        ],
        [
            "act15sre",
            "Invitation to Wine - Rerun",
            1672560000
        ],
        [
            "camp_r_14",
            "Research Base Hanger",
            1673208000
        ],
        [
            "act2bossrush",
            "Trials for Navigator #2",
            1673337600
        ],
        [
            "act23side",
            "Where Vernal Winds Will Never Blow",
            1673928000
        ],
        [
            "act1sandbox",
            "Reclamation Algorithm - Fire Within the Sand",
            1674979200
        ],
        [
            "RA#1",
            "RA#1 : Reclamation Algorithm - Fire Within the Sand",
            1674979200
        ],
        [
            "act14mini",
            "A Death in Chunfen",
            1676361600
        ],
        [
            "act16sre",
            "Guide Ahead - Rerun",
            1676966400
        ],
        [
            "camp_r_15",
            "Lungmen Commercial District",
            1678046400
        ],
        [
            "act24side",
            "A Flurry to the Flame",
            1678161600
        ],
        [
            "CC#12",
            "CC#12 : Operation Basepoint",
            1679385600
        ],
        [
            "act4fun",
            "April Fools' Day Event 2023 (EN : 2024)",
            1680336000
        ],
        [
            "main_12",
            "Episode 12 : All Quiet Under the Thunder",
            1680753600
        ],
        [
            "act17sre",
            "Stultifera Navis - Rerun",
            1681977600
        ],
        [
            "camp_r_16",
            "Rest Avenue",
            1682884800
        ],
        [
            "act25side",
            "Lone Trail",
            1682913600
        ],
        [
            "act38d1",
            "Pinch-Out Experimental Operation",
            1684742400
        ],
        [
            "PinchOut",
            "Pinch-Out Experimental Operation",
            1684742400
        ],
        [
            "act26side",
            "Hortus de Escapismo",
            1686196800
        ],
        [
            "act18sre",
            "Lingering Echoes - Rerun",
            1687248000
        ],
        [
            "act15mini",
            "The Black Forest Wills A Dream",
            1688616000
        ],
        [
            "camp_r_17",
            "Ashy Marsh",
            1688932800
        ],
        [
            "IS#4",
            "IS#4 : Expeditioner's Jǫklumarkar",
            1689235200
        ],
        [
            "act19sre",
            "Dorothy's Vision - Retrospection",
            1689667200
        ],
        [
            "act27side",
            "So Long, Adele: Home Away From Home",
            1690862400
        ],
        [
            "act3bossrush",
            "Trials for Navigator #3",
            1692345600
        ],
        [
            "act20sre",
            "Ideal City: Endless Carnival - Rerun",
            1693468800
        ],
        [
            "camp_r_18",
            "The Special Little Aquapit'",
            1693771200
        ],
        [
            "act28side",
            "Come Catastrophes or Wakes of Vultures",
            1693886400
        ],
        [
            "act42d0",
            "DOS : Design of Strife",
            1695801600
        ],
        [
            "main_13",
            "Episode 13 : The Whirlpool that is Passion",
            1696737600
        ],
        [
            "act21sre",
            "Il Siracusano - Retrospection",
            1697961600
        ],
        [
            "camp_r_19",
            "Decaying Wastes",
            1698609600
        ],
        [
            "act29side",
            "Zwillingstürme im Herbst",
            1698811200
        ],
        [
            "CCBP#01",
            "CCBP#01 : Battleplan Pyrolysis",
            1700553600
        ],
        [
            "act30side",
            "The Rides to Lake Silberneherze",
            1701748800
        ],
        [
            "act22sre",
            "What the Firelight Casts - Retrospection",
            1703232000
        ],
        [
            "camp_r_20",
            "Mountain-Ringed Border Town",
            1704657600
        ],
        [
            "act16mini",
            "To the Grinning Valley",
            1704787200
        ],
        [
            "act23sre",
            "Where Vernal Winds Will Never Blow - Rerun",
            1705564800
        ],
        [
            "act31side",
            "Here A People Sows",
            1706760000
        ],
        [
            "RA#2",
            "RA#2 : Reclamation Algorithm - Tales Within the Sand",
            1706929200
        ],
        [
            "act4bossrush",
            "Trials for Navigator #4",
            1708588800
        ],
        [
            "camp_r_21",
            "New Hotel Avenue",
            1709496000
        ],
        [
            "act32side",
            "Operation Lucent Arrowhead",
            1709784000
        ],
        [
            "act1r6sre",
            "Operation Originium Dust - Retrospection",
            1711008000
        ],
        [
            "CCBP#02",
            "CCBP#02 : Battleplan Underdawn",
            1711612800
        ],
        [
            "act5fun",
            "April Fools' Day Event 2024 (EN : 2025)",
            1711958400
        ],
        [
            "act33side",
            "Babel",
            1712808000
        ],
        [
            "camp_r_22",
            "'Eccentricity' Laboratory",
            1714334400
        ],
        [
            "main_14",
            "Episode 14 : Absolved Will Be the Seekers",
            1714536000
        ],
        [
            "act2vmulti",
            "Rhodes Island Icebreaker Games",
            1715760000
        ],
        [
            "act25sre",
            "Lone Trail - Rerun",
            1716537600
        ],
        [
            "act34side",
            "Path of Life",
            1717560000
        ],
        [
            "act26sre",
            "Hortus de Escapismo - Retrospection",
            1719302400
        ],
        [
            "camp_r_23",
            "Burning District",
            1720382400
        ],
        [
            "act17mini",
            "A Kazdelian Rescue",
            1720497600
        ],
        [
            "IS#5",
            "IS#5 : Sarkaz's Furnaceside Fables",
            1721116800
        ],
        [
            "act35side",
            "Adventure That Cannot Wait for the Sun",
            1722484800
        ],
        [
            "Mechanic",
            "Training Ground",
            1722484800
        ],
        [
            "act27sre",
            "So Long, Adele: Home Away From Home - Retrospection",
            1724313600
        ],
        [
            "camp_r_24",
            "Icebound Valley",
            1725220800
        ],
        [
            "act36side",
            "Delicious On Terra",
            1725249600
        ],
        [
            "act28sre",
            "Come Catastrophes or Wakes of Vultures - Rerun",
            1726732800
        ],
        [
            "act1vecb",
            "Vector Breakthrough",
            1727424000
        ],
        [
            "act37side",
            "Ending a Grand Overture",
            1728446400
        ],
        [
            "camp_r_25",
            "Cityway 66",
            1730059200
        ],
        [
            "act38side",
            "I Portatori dei Velluti",
            1730433600
        ],
        [
            "act1vautochess",
            "Stronghold Protocol",
            1731657600
        ],
        [
            "act29sre",
            "Zwillingstürme im Herbst - Rerun",
            1732521600
        ],
        [
            "act39side",
            "Exodus from the Pale Sea",
            1733371200
        ],
        [
            "act30sre",
            "The Rides to Lake Silberneherze - Rerun",
            1734595200
        ],
        [
            "act1arcade",
            "Poly Vision Museum",
            1735459200
        ],
        [
            "camp_r_26",
            "Paddy Field 9-7",
            1736107200
        ],
        [
            "act40side",
            "Such is the Joy of Our Reunion",
            1737518400
        ],
        [
            "CCBP#03",
            "CCBP#03 : Battleplan Extinguished Sins",
            1738742400
        ],
        [
            "act18mini",
            "See You Soon",
            1739520000
        ],
        [
            "act31sre",
            "Here A People Sows - Rerun",
            1740384000
        ],
        [
            "camp_r_27",
            "Kurfürstenplatz",
            1740945600
        ],
        [
            "act41side",
            "When Elegies Are Ashes",
            1741320000
        ],
        [
            "act1multi",
            "Icebreaker Games #1",
            1742457600
        ],
        [
            "act6fun",
            "April Fools' Day Event 2025 (EN : 2026)",
            1743494400
        ],
        [
            "act33sre",
            "Babel - Rerun",
            1745222400
        ],
        [
            "act1enemyduel",
            "Duel Channel: Green Grass",
            1745674200
        ],
        [
            "camp_r_28",
            "大巴扎",
            1745784000
        ],
        [
            "act42side",
            "The Masses' Travels",
            1746072000
        ],
        [
            "act1break",
            "Vector Breakthrough #1 : Mechanist",
            1747296000
        ],
        [
            "act43side",
            "Act or Die",
            1749096000
        ],
        [
            "act34sre",
            "Path of Life - Rerun",
            1750320000
        ],
        [
            "act5bossrush",
            "Trials for Navigator #5",
            1750752000
        ],
        [
            "act19mini",
            "Fantasy in The Mirage",
            1751947200
        ],
        [
            "IS#6",
            "IS#6 : Sui's Garden of Grotesqueries",
            1752566400
        ],
        [
            "camp_r_29",
            "鳞骸盐漠 ",
            1753646400
        ],
        [
            "act44side",
            "Ato",
            1754107200
        ],
        [
            "CCBP#04",
            "CCBP#04 : Battleplan Arclight",
            1755158400
        ],
        [
            "act35sre",
            "Adventure That Cannot Wait for the Sun - Rerun",
            1756065600
        ],
        [
            "act2enemyduel",
            "Duel Channel: Honeydew",
            1756368000
        ],
        [
            "act45side",
            "Somniloquium Serenum",
            1756958400
        ],
        [
            "act37sre",
            "Ending a Grand Overture - Rerun",
            1758268800
        ],
        [
            "act1vhalfidle",
            "Rebuilding Mandate",
            1758787200
        ],
        [
            "act2multi",
            "Icebreaker Games #2",
            1761033600
        ]
    ]
}